fastapi_starter/__init__.py
fastapi_starter/generator.py
hitesh_fastapi_starter-1.1.7.dist-info/licenses/LICENSE
hitesh_fastapi_starter-1.1.7.dist-info/METADATA
hitesh_fastapi_starter-1.1.7.dist-info/WHEEL
hitesh_fastapi_starter-1.1.7.dist-info/entry_points.txt
hitesh_fastapi_starter-1.1.7.dist-info/top_level.txt
hitesh_fastapi_starter-1.1.7.dist-info/RECORD
