Metadata-Version: 2.4
Name: hitesh-fastapi-starter
Version: 1.1.7
Summary: Generate a FastAPI starter project structure. This version solve many bugs and security 
Home-page: https://github.com/Hitesh26682/hitesh-fastapi-starter
Author: Hitesh Ladumor
Author-email: thingswhat88@gmail.com
Classifier: Programming Language :: Python :: 3
Classifier: License :: OSI Approved :: MIT License
Classifier: Operating System :: OS Independent
Requires-Python: >=3.7
License-File: LICENSE
Requires-Dist: fastapi
Dynamic: author
Dynamic: author-email
Dynamic: classifier
Dynamic: description
Dynamic: description-content-type
Dynamic: home-page
Dynamic: license-file
Dynamic: requires-dist
Dynamic: requires-python
Dynamic: summary
